<?xml version="1.0" encoding="UTF-8"?>
<con:soapui-project id="5029cc28-b6e6-4750-ad60-b0858eae3ec8" activeEnvironment="Default" name="REST Project 1" soapui-version="5.5.0" xmlns:con="http://eviware.com/soapui/config"><con:settings/><con:interface xsi:type="con:RestService" id="2f3a5820-3218-4a48-8759-697f38bdc1ab" wadlVersion="http://wadl.dev.java.net/2009/02" name="" type="rest" xmlns:xsi="http://www.w3.org/2001/XMLSchema-instance"><con:settings/><con:definitionCache type="TEXT" rootPart=""/><con:endpoints/><con:resource name="Cms" path="/cms" id="1b556752-9cdb-4d19-8ee9-824aa85033a0"><con:settings/><con:parameters/><con:method name="Cms 1" id="bd38e38e-a652-474b-a89a-88a99317cc9e" method="GET"><con:settings/><con:parameters/><con:request name="Request 1" id="7d3b63a2-5f3b-488e-a081-f6839f3f573e" mediaType="application/json"><con:settings/><con:request/><con:credentials><con:authType>No Authorization</con:authType></con:credentials><con:jmsConfig JMSDeliveryMode="PERSISTENT"/><con:jmsPropertyConfig/><con:parameters/></con:request></con:method></con:resource></con:interface><con:properties/><con:wssContainer/><con:oAuth2ProfileContainer/><con:oAuth1ProfileContainer/></con:soapui-project>